gratisdns
