Metadata-Version: 2.1
Name: python-gratisdns
Version: 0.3
Summary: Unofficial library for interfacing with the gratisdns.dk web interface
Home-page: https://github.com/laudrup/python-gratisdns
Author: Mads Sülau Jørgensen, Kasper Laudrup
Author-email: mads@sulau.dk, laudrup@stacktrace.dk
License: MIT
Keywords: gratisdns,dns
Platform: UNKNOWN
Classifier: Development Status :: 4 - Beta
Classifier: License :: OSI Approved :: MIT License
Classifier: Operating System :: POSIX :: Linux
Classifier: Operating System :: Microsoft :: Windows
Classifier: Programming Language :: Python :: 3 :: Only
Classifier: Programming Language :: Python :: 3.6
Classifier: Programming Language :: Python :: 3.7
Classifier: Topic :: Software Development :: Libraries
